pygroupmeapi/__init__.py
pygroupmeapi/chat.py
pygroupmeapi/common_utils.py
pygroupmeapi/emoji_utils.py
pygroupmeapi/groupme.py
pygroupmeapi/message.py
pygroupmeapi/time_functions.py
pygroupmeapi-2.0.1.dist-info/METADATA
pygroupmeapi-2.0.1.dist-info/WHEEL
pygroupmeapi-2.0.1.dist-info/licenses/LICENSE
pygroupmeapi-2.0.1.dist-info/RECORD
