Metadata-Version: 2.4
Name: pygroupmeapi
Version: 2.0.1
Summary: A Python wrapper around GroupMe's REST API
Project-URL: Homepage, https://github.com/pbuterba/pygroupmeapi
Project-URL: Issues, https://github.com/pbuterba/pygroupmeapi/issues
Author-email: Preston Buterbaugh <pbuterba.corp@gmail.com>
License-Expression: GPL-3.0
License-File: LICENSE
Classifier: Operating System :: OS Independent
Classifier: Programming Language :: Python :: 3
Requires-Python: >=3.10
Requires-Dist: requests
